atap_cloud_downloader/CloudDownloader.py
atap_cloud_downloader/__init__.py
atap_cloud_downloader-0.1.2.dist-info/LICENSE
atap_cloud_downloader-0.1.2.dist-info/METADATA
atap_cloud_downloader-0.1.2.dist-info/WHEEL
atap_cloud_downloader-0.1.2.dist-info/RECORD
